redarch/__init__.py
redarch/cli.py
redarch-0.1.0.dist-info/LICENSE
redarch-0.1.0.dist-info/METADATA
redarch-0.1.0.dist-info/WHEEL
redarch-0.1.0.dist-info/entry_points.txt
redarch-0.1.0.dist-info/RECORD
